Metadata-Version: 2.1
Name: azure-ai-mlmonitoring
Version: 0.1.0a3
Summary: Azure Machine Learning Model Monitoring SDK V2
Author: Microsoft Corporation
Author-email: azuremlsdk@microsoft.com
License: MIT License
Keywords: AzureMachineLearning,ModelMonitoring
Platform: any
Classifier: Development Status :: 2 - Pre-Alpha
Classifier: Intended Audience :: Developers
Classifier: Natural Language :: English
Classifier: Operating System :: OS Independent
Classifier: Programming Language :: Python
Classifier: Programming Language :: Python :: 3.7
Classifier: Programming Language :: Python :: 3.8
Classifier: Programming Language :: Python :: 3.9
Classifier: Programming Language :: Python :: 3.10
Classifier: License :: OSI Approved :: MIT License
Requires-Dist: requests (==2.28.1)
Provides-Extra: setup
Requires-Dist: setuptools (>=40.4.3) ; extra == 'setup'
Requires-Dist: pip (~=20.3) ; extra == 'setup'
Requires-Dist: wheel ; extra == 'setup'
Provides-Extra: test
Requires-Dist: pytest-subtests ; extra == 'test'
Requires-Dist: pytest-cov ; extra == 'test'
Requires-Dist: pytest-xdist ; extra == 'test'
Requires-Dist: numpy ; extra == 'test'
Requires-Dist: pandas ; extra == 'test'
